mms/__init__.py
mms/base_logger.py
mms/bq_handler.py
mms/datastore_handler.py
mms/gcp_bearer_token.py
mms/gcp_secret_manager.py
mms/kubeflow_handler.py
mms/mms_fifa.py
mms/pubsub_handler.py
mms/redis_handler.py
mms/logger/__init__.py
mms/logger/app_engine_logger.py
mms/logger/cloud_function_logger.py
mms/logger/cloud_run_logger.py
mms/logger/composer_logger.py
mms/logger/compute_engine_logger.py
mms/logger/dataproc_logger.py
mms/logger/kubernetes_logger.py
mms/test/__init__.py
mms/test/test_kms.py
mms/test/test_logger.py
mms_pip-0.8.4.7.dist-info/LICENSE.md
mms_pip-0.8.4.7.dist-info/METADATA
mms_pip-0.8.4.7.dist-info/WHEEL
mms_pip-0.8.4.7.dist-info/top_level.txt
mms_pip-0.8.4.7.dist-info/RECORD
