Metadata-Version: 2.1
Name: mms-pip
Version: 0.8.4.7
Summary: A custom MMS Analytics module for Python3 by the Touchpoint Analytics & Data Discovery
Home-page: https://github.com/MediaMarktSaturn/mms-pip
Author: Josef Goppold, Tobias Hoke
Author-email: goppold@mediamarktsaturn.com, hoke@mediamarktsaturn.com
License: UNKNOWN
Platform: UNKNOWN
Classifier: Programming Language :: Python :: 3
Classifier: License :: OSI Approved :: MIT License
Classifier: Operating System :: OS Independent
Requires-Dist: google-cloud-logging (>=1.10.0)
Requires-Dist: google-cloud-datastore (>=1.8.0)
Requires-Dist: google-cloud-bigquery (>=1.16.0)
Requires-Dist: google-cloud-storage (>=1.15.0)
Requires-Dist: google-cloud-kms (>=1.2.1)
Requires-Dist: gcsfs (>=0.1.2)
Requires-Dist: pyarrow (>=0.12.1)
Requires-Dist: pandas (>=0.24.1)
Requires-Dist: redis (>=3.0.1)
Requires-Dist: google-auth (>=1.5.0)
Requires-Dist: pyjwt (>=1.7.1)
Requires-Dist: cryptography (>=2.8)
Requires-Dist: google-cloud-secret-manager (>=2.0.0)
Requires-Dist: google-cloud-pubsub (>=2.1.0)
Requires-Dist: kfp (==1.6.5)
